fastapi_resource.py
fastapi_resource-0.1.dist-info/LICENSE
fastapi_resource-0.1.dist-info/METADATA
fastapi_resource-0.1.dist-info/WHEEL
fastapi_resource-0.1.dist-info/top_level.txt
fastapi_resource-0.1.dist-info/RECORD
