Metadata-Version: 2.1
Name: fastapi-resource
Version: 0.1
Summary: Resource init and shutdown for FastAPI
Home-page: http://github.com/brannt/fastapi_resource
Author: Artem Gorokhov
Author-email: branntart@gmail.com
License: MIT
Platform: UNKNOWN
License-File: LICENSE
